{
"type": "FeatureCollection",
"name": "supermarket",
"crs": { "type": "name", "properties": { "name": "urn:ogc:def:crs:OGC:1.3:CRS84" } },
"features": [
{ "type": "Feature", "properties": { "full_id": "n1392117416", "osm_id": "1392117416", "osm_type": "node", "shop": "supermarket", "self_checkout": null, "ref:FR:SIRET": null, "ref:FR:SIREN": null, "ref:FR:NAF": null, "elevator": null, "brand:wikipedia": null, "brand:wikidata": null, "brand:website": null, "brand": null, "automatic_door": null, "wheelchair": "yes", "website": "https://lelefan.org/", "toilets": "no", "stroller": "yes", "second_hand": "no", "phone": "+33 9 72 64 91 14", "payment:debit_cards": "yes", "payment:credit_cards": "yes", "payment:cash:XLT-CARN": "yes", "payment:cash": "yes", "organic": "yes", "operator:type": "cooperative", "opening_hours": "Mo-Fr 10:00-13:30, 16:00-19:00; We 10:00-13:30, 16:00-20:30; Sa 10:00-14:30,17:00-19:00", "name": "L'Éléfàn", "level": "0", "internet_access": "no", "email": "contact@lelefan.org", "currency:XLT": "CARN", "currency:EUR": "yes", "contact:instagram": "lelefandegrenoble", "contact:facebook": "lelefandegrenoble", "check_date": "2024-12-31", "change:XLT-CARN": "yes", "bulk_purchase": "yes", "building:levels": "0", "addr:street": "Avenue Marcelin Berthelot", "addr:postcode": "38100", "addr:housenumber": "32", "addr:city": "Grenoble", "access": "permissive" }, "geometry": { "type": "Point", "coordinates": [ 5.7304083, 45.1750672 ] } },
{ "type": "Feature", "properties": { "full_id": "n4221545389", "osm_id": "4221545389", "osm_type": "node", "shop": "supermarket", "self_checkout": "yes", "ref:FR:SIRET": "34326262218893", "ref:FR:SIREN": "343262622", "ref:FR:NAF": "47.11D", "elevator": "yes", "brand:wikipedia": "en:Lidl", "brand:wikidata": "Q151954", "brand:website": "http://www.lidl.fr", "brand": "Lidl", "automatic_door": "motion", "wheelchair": "yes", "website": null, "toilets": null, "stroller": null, "second_hand": null, "phone": "+33 800005435", "payment:debit_cards": null, "payment:credit_cards": null, "payment:cash:XLT-CARN": null, "payment:cash": null, "organic": null, "operator:type": null, "opening_hours": "Mo-Sa 08:30-19:30", "name": "Lidl", "level": "0.5", "internet_access": null, "email": null, "currency:XLT": null, "currency:EUR": null, "contact:instagram": null, "contact:facebook": null, "check_date": "2026-02-04", "change:XLT-CARN": null, "bulk_purchase": null, "building:levels": null, "addr:street": null, "addr:postcode": null, "addr:housenumber": null, "addr:city": null, "access": null }, "geometry": { "type": "Point", "coordinates": [ 5.7220062, 45.1720868 ] } }
]
}
